pyteomics.biolccc-1.5.1-py3.9-nspkg.pth
pyteomics/_biolccc.cpython-39-x86_64-linux-gnu.so
pyteomics/biolccc.py
pyteomics.biolccc-1.5.1.dist-info/namespace_packages.txt
pyteomics.biolccc-1.5.1.dist-info/top_level.txt
pyteomics.biolccc-1.5.1.dist-info/RECORD
pyteomics.biolccc-1.5.1.dist-info/WHEEL
pyteomics.biolccc-1.5.1.dist-info/METADATA
