Metadata-Version: 2.1
Name: pyteomics.biolccc
Version: 1.5.1
Summary: Bindings for the libBioLCCC
Home-page: http://theorchromo.ru
Author: Anton Goloborodko
Author-email: goloborodko.anton@gmail.com
License: License :: Free for non-commercial use
Platform: UNKNOWN
Classifier: Intended Audience :: Science/Research
Classifier: Topic :: Scientific/Engineering :: Bio-Informatics
Classifier: Topic :: Scientific/Engineering :: Chemistry
Classifier: Topic :: Scientific/Engineering :: Physics
